spraakbanken/__init__.py
spraakbanken/__main__.py
spraakbanken/dataset.py
spraakbanken/dataset_custom_rules.py
spraakbanken/sprakbanken_scraping.py
spraakbanken/util.py
spraakbanken_downloader-0.2.0.dist-info/LICENSE
spraakbanken_downloader-0.2.0.dist-info/METADATA
spraakbanken_downloader-0.2.0.dist-info/WHEEL
spraakbanken_downloader-0.2.0.dist-info/top_level.txt
spraakbanken_downloader-0.2.0.dist-info/RECORD
