Metadata-Version: 2.1
Name: spraakbanken-downloader
Version: 0.2.0
Summary: Downloader and tools for Spraakbanken data
Author-email: tollef jørgensen <tollefj@gmail.com>
Project-URL: Homepage, https://github.com/scribe-project/spraakbanken-downloader
Project-URL: Bug tracker, https://github.com/scribe-project/spraakbanken-downloader/issues
Classifier: Programming Language :: Python :: 3
Classifier: License :: OSI Approved :: MIT License
Classifier: Operating System :: OS Independent
Requires-Python: >=3.7
License-File: LICENSE
